bin/drupal-scout
drupal_scout/__init__.py
drupal_scout/application.py
drupal_scout/exceptions.py
drupal_scout/module.py
drupal_scout/worker.py
drupal_scout/workers_manager.py
drupal_scout/formatters/formatter.py
drupal_scout/formatters/formatterfactory.py
drupal_scout/formatters/jsonformatter.py
drupal_scout/formatters/suggestformatter.py
drupal_scout/formatters/tableformatter.py
drupal_scout/tests/__init__.py
drupal_scout/tests/test_application.py
drupal_scout/tests/test_worker.py
drupal_scout-1.0.2.data/scripts/drupal-scout
drupal_scout-1.0.2.dist-info/LICENSE.txt
drupal_scout-1.0.2.dist-info/METADATA
drupal_scout-1.0.2.dist-info/WHEEL
drupal_scout-1.0.2.dist-info/top_level.txt
drupal_scout-1.0.2.dist-info/RECORD
