Metadata-Version: 2.1
Name: drupal-scout
Version: 1.0.2
Summary: Scout out for transitive versions of Drupal modules for the upgrade of the core.
Author-email: "Andrew [R-Tech] Tsyhaniuk" <in0mad91@gmail.com>
License: MIT License
Project-URL: Homepage, https://github.com/rtech91/drupal-scout
Project-URL: Bug Tracker, https://github.com/rtech91/drupal-scout/issues
Keywords: drupal,scout,upgrade,core,transitive,dependencies
Classifier: Development Status :: 5 - Production/Stable
Classifier: Environment :: Console
Classifier: Intended Audience :: Developers
Classifier: License :: OSI Approved :: MIT License
Classifier: Operating System :: OS Independent
Classifier: Programming Language :: Python :: 3
Classifier: Topic :: Software Development :: Build Tools
Classifier: Topic :: Software Development :: Libraries :: Python Modules
Classifier: Topic :: Utilities
Requires-Python: >=3.10
License-File: LICENSE.txt
Requires-Dist: jq
Requires-Dist: argparse
Requires-Dist: requests
Requires-Dist: packaging
Requires-Dist: prettytable
Requires-Dist: termcolor
Provides-Extra: dev
Requires-Dist: nose ; extra == 'dev'
Requires-Dist: coverage ; extra == 'dev'
Requires-Dist: pipdeptree ; extra == 'dev'
Requires-Dist: pip-autoremove ; extra == 'dev'
